package_test/__init__.py
package_test/main.py
my_demo_617_202013-2020.11.14.dist-info/METADATA
my_demo_617_202013-2020.11.14.dist-info/WHEEL
my_demo_617_202013-2020.11.14.dist-info/top_level.txt
my_demo_617_202013-2020.11.14.dist-info/RECORD
