Metadata-Version: 2.1
Name: my-demo-617-202013
Version: 2020.11.14
Summary: A demo for python packaging.
Home-page: https://github.com/***/***
Author: liuyaqi
Author-email: yaqi_617@163.com
License: JDJD
Keywords: demo
Platform: UNKNOWN
